odoo_install/instalaservicio.py
odoo_install/configuranginx.py
odoo_install/instaladorapt.py
odoo_install/postgres.py
odoo_install/stopcalling.py
odoo_install/replace.py
odoo_install/loggeador.py
odoo_install/odoo_install.py
odoo_install/dependencias.py
odoo_install/_init_.py
odoo_install/instalagit.py
odooinstall-0.4.2a1.dist-info/DESCRIPTION.rst
odooinstall-0.4.2a1.dist-info/dependency_links.txt
odooinstall-0.4.2a1.dist-info/METADATA
odooinstall-0.4.2a1.dist-info/WHEEL
odooinstall-0.4.2a1.dist-info/top_level.txt
odooinstall-0.4.2a1.dist-info/pbr.json
odooinstall-0.4.2a1.dist-info/metadata.json
odooinstall-0.4.2a1.dist-info/RECORD
odooinstall/instalaservicio.py
odooinstall/configuranginx.py
odooinstall/instaladorapt.py
odooinstall/postgres.py
odooinstall/menu.py
odooinstall/stopcalling.py
odooinstall/replace.py
odooinstall/loggeador.py
odooinstall/odoo_install.py
odooinstall/dependencias.py
odooinstall/_init_.py
odooinstall/instalagit.py
